Workbook

Sheet Dataset_final
A1: Date | B1: btc_usd | C1: btc_return | D1: sp500 | E1: sp500_return | F1: gold_usd | G1: gold_return | H1: fed_funds_rate | I1: fed_funds_change | J1: cpi_index | K1: inflation_yoy | L1: m2_money_stock | M1: m2_growth_yoy | N1: halving_window_3m | O1: btc_volatility_3m
A2: 42370 | B2: 368.77 | D2: 1940.24 | F2: 1116.4 | H2: 0.34 | J2: 237.652 | L2: 12518.5 | N2: 0
A3: 42401 | B3: 437.7 | C3: =LN(B3/B2) -> 0.1713606 | D3: 1932.23 | E3: =LN(D3/D2) -> -0.0041369004 | F3: 1233.9 | G3: =LN(F3/F2) -> 0.10007066 | H3: 0.38 | I3: =H3-H2 -> 0.04 | J3: 237.336 | L3: 12603.9 | N3: 0
A4: 42430 | B4: 416.73 | C4: =LN(B4/B3) -> -0.049095214 | D4: 2059.74 | E4: =LN(D4/D3) -> 0.063904985 | F4: 1234.2 | G4: =LN(F4/F3) -> 0.00024310198 | H4: 0.36 | I4: =H4-H3 -> -0.02 | J4: 238.08 | L4: 12661.8 | N4: 0 | O4: =_xlfn.STDEV.S(C2:C4) -> 0.1558858
A5: 42461 | B5: 448.32 | C5: =LN(B5/B4) -> 0.073068733 | D5: 2065.3 | E5: =LN(D5/D4) -> 0.0026957331 | F5: 1289.2 | G5: =LN(F5/F4) -> 0.043598884 | H5: 0.37 | I5: =H5-H4 -> 0.01 | J5: 238.992 | L5: 12743.2 | N5: 0 | O5: =_xlfn.STDEV.S(C3:C5) -> 0.11044311
A6: 42491 | B6: 531.39 | C6: =LN(B6/B5) -> 0.16998895 | D6: 2096.95 | E6: =LN(D6/D5) -> 0.015208414 | F6: 1214.8 | G6: =LN(F6/F5) -> -0.059442417 | H6: 0.37 | I6: =H6-H5 -> 0 | J6: 239.557 | L6: 12802 | N6: 0 | O6: =_xlfn.STDEV.S(C4:C6) -> 0.10978421
A7: 42522 | B7: 673.34 | C7: =LN(B7/B6) -> 0.23675419 | D7: 2098.86 | E7: =LN(D7/D6) -> 0.00091043214 | F7: 1318.4 | G7: =LN(F7/F6) -> 0.081839426 | H7: 0.38 | I7: =H7-H6 -> 0.01 | J7: 240.222 | L7: 12852.5 | N7: 0 | O7: =_xlfn.STDEV.S(C5:C7) -> 0.082304368
A8: 42552 | B8: 624.68 | C8: =LN(B8/B7) -> -0.075010884 | D8: 2173.6 | E8: =LN(D8/D7) -> 0.034990439 | F8: 1349 | G8: =LN(F8/F7) -> 0.022944697 | H8: 0.39 | I8: =H8-H7 -> 0.01 | J8: 240.101 | L8: 12911.9 | N8: 1 | O8: =_xlfn.STDEV.S(C6:C8) -> 0.16415439
A9: 42583 | B9: 575.47 | C9: =LN(B9/B8) -> -0.08205242 | D9: 2170.95 | E9: =LN(D9/D8) -> -0.0012199194 | F9: 1306.9 | G9: =LN(F9/F8) -> -0.031705657 | H9: 0.4 | I9: =H9-H8 -> 0.01 | J9: 240.545 | L9: 12989.7 | N9: 1 | O9: =_xlfn.STDEV.S(C7:C9) -> 0.18206441
A10: 42614 | B10: 609.74 | C10: =LN(B10/B9) -> 0.057845539 | D10: 2168.27 | E10: =LN(D10/D9) -> -0.0012352452 | F10: 1313.3 | G10: =LN(F10/F9) -> 0.004885133 | H10: 0.4 | I10: =H10-H9 -> 0 | J10: 241.176 | L10: 13054.9 | N10: 1 | O10: =_xlfn.STDEV.S(C8:C10) -> 0.078816085
A11: 42644 | B11: 700.97 | C11: =LN(B11/B10) -> 0.13943245 | D11: 2126.15 | E11: =LN(D11/D10) -> -0.019616782 | F11: 1271.5 | G11: =LN(F11/F10) -> -0.032345748 | H11: 0.4 | I11: =H11-H10 -> 0 | J11: 241.741 | L11: 13122.8 | N11: 0 | O11: =_xlfn.STDEV.S(C9:C11) -> 0.11201444
A12: 42675 | B12: 745.69 | C12: =LN(B12/B11) -> 0.061844874 | D12: 2198.81 | E12: =LN(D12/D11) -> 0.033603472 | F12: 1170.8 | G12: =LN(F12/F11) -> -0.08251003 | H12: 0.41 | I12: =H12-H11 -> 0.01 | J12: 242.026 | L12: 13208.7 | N12: 0 | O12: =_xlfn.STDEV.S(C10:C12) -> 0.045993209
A13: 42705 | B13: 963.74 | C13: =LN(B13/B12) -> 0.25651158 | D13: 2238.83 | E13: =LN(D13/D12) -> 0.018037103 | F13: 1150 | G13: =LN(F13/F12) -> -0.017925333 | H13: 0.54 | I13: =H13-H12 -> 0.13 | J13: 242.637 | L13: 13234.9 | N13: 0 | O13: =_xlfn.STDEV.S(C11:C13) -> 0.09799871
A14: 42736 | B14: 970.4 | C14: =LN(B14/B13) -> 0.0068868089 | D14: 2278.87 | E14: =LN(D14/D13) -> 0.017726298 | F14: 1208.6 | G14: =LN(F14/F13) -> 0.049700723 | H14: 0.65 | I14: =H14-H13 -> 0.11 | J14: 243.618 | K14: =J14/J2-1 -> 0.025103933 | L14: 13315.7 | M14: =L14/L2-1 -> 0.063681751 | N14: 0 | O14: =_xlfn.STDEV.S(C12:C14) -> 0.13116659
A15: 42767 | B15: 1179.97 | C15: =LN(B15/B14) -> 0.19553594 | D15: 2363.64 | E15: =LN(D15/D14) -> 0.036523098 | F15: 1252.6 | G15: =LN(F15/F14) -> 0.035758726 | H15: 0.66 | I15: =H15-H14 -> 0.01 | J15: 244.006 | K15: =J15/J3-1 -> 0.028103617 | L15: 13394.8 | M15: =L15/L3-1 -> 0.062750419 | N15: 0 | O15: =_xlfn.STDEV.S(C13:C15) -> 0.13014034
A16: 42795 | B16: 1071.79 | C16: =LN(B16/B15) -> -0.096158866 | D16: 2362.72 | E16: =LN(D16/D15) -> -0.00038930594 | F16: 1247.3 | G16: =LN(F16/F15) -> -0.004240176 | H16: 0.79 | I16: =H16-H15 -> 0.13 | J16: 243.892 | K16: =J16/J4-1 -> 0.024411962 | L16: 13463.6 | M16: =L16/L4-1 -> 0.06332433 | N16: 0 | O16: =_xlfn.STDEV.S(C14:C16) -> 0.14792609
A17: 42826 | B17: 1347.89 | C17: =LN(B17/B16) -> 0.22921026 | D17: 2384.2 | E17: =LN(D17/D16) -> 0.0090501406 | F17: 1266.1 | G17: =LN(F17/F16) -> 0.014960094 | H17: 0.9 | I17: =H17-H16 -> 0.11 | J17: 244.193 | K17: =J17/J5-1 -> 0.021762235 | L17: 13521.7 | M17: =L17/L5-1 -> 0.061091406 | N17: 0 | O17: =_xlfn.STDEV.S(C15:C17) -> 0.17892498
A18: 42856 | B18: 2286.41 | C18: =LN(B18/B17) -> 0.5284425 | D18: 2411.8 | E18: =LN(D18/D17) -> 0.011509718 | F18: 1272 | G18: =LN(F18/F17) -> 0.0046491554 | H18: 0.91 | I18: =H18-H17 -> 0.01 | J18: 244.004 | K18: =J18/J6-1 -> 0.018563432 | L18: 13568.9 | M18: =L18/L6-1 -> 0.059904702 | N18: 0 | O18: =_xlfn.STDEV.S(C16:C18) -> 0.31239181
A19: 42887 | B19: 2480.84 | C19: =LN(B19/B18) -> 0.081614311 | D19: 2423.41 | E19: =LN(D19/D18) -> 0.0048022826 | F19: 1240.7 | G19: =LN(F19/F18) -> -0.024914728 | H19: 1.04 | I19: =H19-H18 -> 0.13 | J19: 244.163 | K19: =J19/J7-1 -> 0.016405658 | L19: 13580.5 | M19: =L19/L7-1 -> 0.056642677 | N19: 0 | O19: =_xlfn.STDEV.S(C17:C19) -> 0.227662
A20: 42917 | B20: 2875.34 | C20: =LN(B20/B19) -> 0.14757372 | D20: 2470.3 | E20: =LN(D20/D19) -> 0.019163962 | F20: 1266.6 | G20: =LN(F20/F19) -> 0.020660409 | H20: 1.15 | I20: =H20-H19 -> 0.11 | J20: 244.243 | K20: =J20/J8-1 -> 0.017251074 | L20: 13643.1 | M20: =L20/L8-1 -> 0.056629931 | N20: 0 | O20: =_xlfn.STDEV.S(C18:C20) -> 0.24120085
A21: 42948 | B21: 4703.39 | C21: =LN(B21/B20) -> 0.4921126 | D21: 2471.65 | E21: =LN(D21/D20) -> 0.00054634306 | F21: 1316.2 | G21: =LN(F21/F20) -> 0.038412652 | H21: 1.16 | I21: =H21-H20 -> 0.01 | J21: 245.183 | K21: =J21/J9-1 -> 0.019281216 | L21: 13697.7 | M21: =L21/L9-1 -> 0.054504723 | N21: 0 | O21: =_xlfn.STDEV.S(C19:C21) -> 0.22044142
A22: 42979 | B22: 4338.71 | C22: =LN(B22/B21) -> -0.080706456 | D22: 2519.36 | E22: =LN(D22/D21) -> 0.019118957 | F22: 1281.5 | G22: =LN(F22/F21) -> -0.02671753 | H22: 1.15 | I22: =H22-H21 -> -0.01 | J22: 246.435 | K22: =J22/J10-1 -> 0.021805652 | L22: 13745.1 | M22: =L22/L10-1 -> 0.052869038 | N22: 0 | O22: =_xlfn.STDEV.S(C20:C22) -> 0.28836913
A23: 43009 | B23: 6468.4 | C23: =LN(B23/B22) -> 0.39935171 | D23: 2575.26 | E23: =LN(D23/D22) -> 0.021945599 | F23: 1267 | G23: =LN(F23/F22) -> -0.011379365 | H23: 1.15 | I23: =H23-H22 -> 0 | J23: 246.626 | K23: =J23/J11-1 -> 0.020207578 | L23: 13800.1 | M23: =L23/L11-1 -> 0.051612461 | N23: 0 | O23: =_xlfn.STDEV.S(C21:C23) -> 0.30745788
A24: 43040 | B24: 10233.6 | C24: =LN(B24/B23) -> 0.45874764 | D24: 2647.58 | E24: =LN(D24/D23) -> 0.027695515 | F24: 1273.2 | G24: =LN(F24/F23) -> 0.0048815151 | H24: 1.16 | I24: =H24-H23 -> 0.01 | J24: 247.284 | K24: =J24/J12-1 -> 0.021724939 | L24: 13843.5 | M24: =L24/L12-1 -> 0.048059234 | N24: 0 | O24: =_xlfn.STDEV.S(C22:C24) -> 0.29580242
A25: 43070 | B25: 14156.4 | C25: =LN(B25/B24) -> 0.32449039 | D25: 2673.61 | E25: =LN(D25/D24) -> 0.0097836039 | F25: 1306.3 | G25: =LN(F25/F24) -> 0.025665297 | H25: 1.3 | I25: =H25-H24 -> 0.14 | J25: 247.805 | K25: =J25/J13-1 -> 0.021299307 | L25: 13881.7 | M25: =L25/L13-1 -> 0.048870789 | N25: 0 | O25: =_xlfn.STDEV.S(C23:C25) -> 0.067276917
... A123: 46054 | B123: 66995.86 | C123: =LN(B123/B122) -> -0.16000954 | D123: 6878.88 | E123: =LN(D123/D122) -> -0.0087061473 | F123: 5230.5 | G123: =LN(F123/F122) -> 0.10399128 | H123: 3.64 | I123: =H123-H122 -> 0 | J123: 327.46 | K123: =J123/J111-1 -> 0.024340041 | L123: 22627 | M123: =L123/L111-1 -> 0.046891989 | N123: 0 | O123: =_xlfn.STDEV.S(C121:C123) -> 0.064092171

Sheet Diccionario_variables
A1: Variable | B1: Descripción | C1: Fuente | D1: Frecuencia final | E1: Transformación aplicada | F1: Justificación en el TFG
A2: fecha | B2: Mes de referencia de la observación. | C2: Elaboración propia a partir de fechas de las series. | D2: Mensual | E2: Unificación al primer día de cada mes. | F2: Permite integrar todas las fuentes en una serie temporal común.
A3: btc_usd | B3: Precio mensual de Bitcoin frente al dólar estadounidense. | C3: Digrin / Yahoo Finance (BTC-USD) | D3: Mensual | E3: Precio en niveles. | F3: Variable principal del estudio.
A4: btc_log_return | B4: Rentabilidad logarítmica mensual de Bitcoin. | C4: Calculada | D4: Mensual | E4: LN(BTC_t / BTC_t-1) | F4: Reduce problemas de escala y permite analizar variaciones relativas.
A5: sp500 | B5: Nivel mensual del índice S&P 500. | C5: Digrin / Yahoo Finance (^GSPC) | D5: Mensual | E5: Precio/índice en niveles. | F5: Proxy del comportamiento del mercado bursátil estadounidense.
A6: sp500_log_return | B6: Rentabilidad logarítmica mensual del S&P 500. | C6: Calculada | D6: Mensual | E6: LN(SP500_t / SP500_t-1) | F6: Permite comparar variaciones del mercado de renta variable con Bitcoin.
A7: gold_usd | B7: Precio mensual del oro/futuro de oro. | C7: Digrin / Yahoo Finance (GC=F) | D7: Mensual | E7: Precio en niveles. | F7: Activo de referencia asociado a comportamiento refugio.
A8: gold_log_return | B8: Rentabilidad logarítmica mensual del oro. | C8: Calculada | D8: Mensual | E8: LN(Gold_t / Gold_t-1) | F8: Permite comparar Bitcoin con un activo refugio tradicional.
A9: fed_funds_rate | B9: Tipo efectivo de los fondos federales de EE. UU. | C9: FRED (FEDFUNDS) | D9: Mensual | E9: Serie en niveles, porcentaje anual. | F9: Representa el entorno de tipos de interés.
A10: fed_funds_change | B10: Cambio mensual del tipo efectivo de fondos federales. | C10: Calculada | D10: Mensual | E10: FEDFUNDS_t - FEDFUNDS_t-1 | F10: Captura variaciones en política monetaria.
A11: cpi_index | B11: Índice de precios al consumo de EE. UU. ajustado estacionalmente. | C11: FRED (CPIAUCSL) | D11: Mensual | E11: Serie en niveles. | F11: Base para calcular inflación interanual.
A12: inflation_yoy | B12: Inflación interanual calculada a partir del CPI. | C12: Calculada | D12: Mensual | E12: CPI_t / CPI_t-12 - 1 | F12: Permite analizar el efecto del contexto inflacionario sobre Bitcoin.
... A16: btc_volatility_3m | B16: Volatilidad móvil de Bitcoin a tres meses. | C16: Calculada | D16: Mensual | E16: Desvest.M de las tres últimas rentabilidades logarítmicas. | F16: Mide la inestabilidad reciente del activo.

Sheet Fuentes_datos
A1: Bloque | B1: Variable/serie | C1: Fuente | D1: URL | E1: Notas
A2: Bitcoin | B2: BTC-USD | C2: Digrin / Yahoo Finance | D2: https://www.digrin.com/stocks/detail/BTC-USD/price | E2: Histórico mensual de precios usado como precio de Bitcoin.
A3: Mercado financiero | B3: ^GSPC | C3: Digrin / Yahoo Finance | D3: https://www.digrin.com/stocks/detail/%5EGSPC/price | E3: Histórico mensual del índice S&P 500.
A4: Mercado financiero | B4: GC=F | C4: Digrin / Yahoo Finance | D4: https://www.digrin.com/stocks/detail/GC%3DF/price | E4: Histórico mensual del futuro de oro usado como referencia del oro.
A5: Macroeconomía | B5: FEDFUNDS | C5: FRED - Federal Reserve Bank of St. Louis | D5: https://fred.stlouisfed.org/data/FEDFUNDS | E5: Tipo efectivo de fondos federales, mensual.
A6: Macroeconomía | B6: CPIAUCSL | C6: FRED - Federal Reserve Bank of St. Louis | D6: https://fred.stlouisfed.org/data/CPIAUCSL | E6: Índice CPI mensual ajustado estacionalmente.
A7: Macroeconomía | B7: M2SL | C7: FRED - Federal Reserve Bank of St. Louis | D7: https://fred.stlouisfed.org/data/M2SL | E7: M2 mensual ajustado estacionalmente, en miles de millones de dólares.
A8: Evento Bitcoin | B8: Halving | C8: Bitbo / Investopedia / elaboración propia | D8: https://charts.bitbo.io/halving-dates/ | E8: Fechas de halving: julio 2016, mayo 2020 y abril 2024; convertidas a dummy mensual.

Sheet Control_limpieza
A1: Fase | B1: Decisión aplicada | C1: Resultado / explicación
A2: Periodo final | B2: Se ha fijado el intervalo 2016-01 a 2026-04. | C2: Se escoge abril de 2026 como último mes para mantener todas las fuentes completas, incluido M2SL.
A3: Frecuencia | B3: Todas las variables se han integrado en frecuencia mensual. | C3: Esto permite combinar datos financieros de mercado con variables macroeconómicas mensuales.
A4: Fechas | B4: Las fechas se han normalizado al primer día de cada mes. | C4: La columna fecha funciona como clave de integración.
A5: Duplicados | B5: Se ha comprobado una observación por mes. | C5: No se han incorporado fechas duplicadas en el dataset final.
A6: Valores ausentes | B6: No quedan valores ausentes en las variables de entrada del dataset final. | C6: La única incidencia detectada en CPIAUCSL para 2025-10 se ha imputado mediante interpolación lineal entre septiembre y noviembre de 2025.
A7: Transformaciones | B7: Se han creado rentabilidades logarítmicas, cambios mensuales, crecimientos interanuales y volatilidad móvil. | C7: Las transformaciones permiten trabajar con variaciones comparables y reducir problemas de escala.
A8: Variables evento | B8: Se ha creado una dummy de ventana de halving de tres meses. | C8: La variable toma valor 1 en el mes del halving y los dos meses posteriores.
A9: Aumento artificial de datos | B9: No se ha aplicado data augmentation sintético. | C9: En series temporales financieras podría alterar la estructura temporal y generar información artificial no observada.
A10: Variables descartadas | B10: No se han incluido variables sin una integración fiable y completa en esta primera base final. | C10: Se priorizan variables trazables y consistentes con el anteproyecto frente a una base excesivamente amplia.

Sheet Analisis_exploratorio
A1: Análisis exploratorio inicial
A3: Variable | B3: Observaciones | C3: Media | D3: Desv. típica | E3: Mínimo | F3: Máximo
A4: btc_usd | B4: =COUNT(Dataset_final!B2:B123) -> 122 | C4: =AVERAGE(Dataset_final!B2:B123) -> 31125.887 | D4: =_xlfn.STDEV.S(Dataset_final!B2:B123) -> 32123.049 | E4: =MIN(Dataset_final!B2:B123) -> 368.77 | F4: =MAX(Dataset_final!B2:B123) -> 115758.2
A5: btc_log_return | B5: =COUNT(Dataset_final!C2:C123) -> 121 | C5: =AVERAGE(Dataset_final!C2:C123) -> 0.042993496 | D5: =_xlfn.STDEV.S(Dataset_final!B3:B124) -> 32133.174 | E5: =MIN(Dataset_final!C2:C123) -> -0.47431401 | F5: =MAX(Dataset_final!C2:C123) -> 0.5284425
A6: sp500 | B6: =COUNT(Dataset_final!D2:D123) -> 122 | C6: =AVERAGE(Dataset_final!D2:D123) -> 3839.1546 | D6: =_xlfn.STDEV.S(Dataset_final!B4:B125) -> 32141.951 | E6: =MIN(Dataset_final!D2:D123) -> 1932.23 | F6: =MAX(Dataset_final!D2:D123) -> 6939.03
A7: sp500_log_return | B7: =COUNT(Dataset_final!E2:E123) -> 121 | C7: =AVERAGE(Dataset_final!E2:E123) -> 0.010459869 | D7: =_xlfn.STDEV.S(Dataset_final!B5:B126) -> 32148.561 | E7: =MIN(Dataset_final!E2:E123) -> -0.13366777 | F7: =MAX(Dataset_final!E2:E123) -> 0.1194209
A8: gold_usd | B8: =COUNT(Dataset_final!F2:F123) -> 122 | C8: =AVERAGE(Dataset_final!F2:F123) -> 1889.6041 | D8: =_xlfn.STDEV.S(Dataset_final!B6:B127) -> 32153.336 | E8: =MIN(Dataset_final!F2:F123) -> 1116.4 | F8: =MAX(Dataset_final!F2:F123) -> 5230.5
A9: gold_log_return | B9: =COUNT(Dataset_final!G2:G123) -> 121 | C9: =AVERAGE(Dataset_final!G2:G123) -> 0.012763617 | D9: =_xlfn.STDEV.S(Dataset_final!B7:B128) -> 32156.618 | E9: =MIN(Dataset_final!G2:G123) -> -0.08251003 | F9: =MAX(Dataset_final!G2:G123) -> 0.10399128
A10: fed_funds_rate | B10: =COUNT(Dataset_final!H2:H123) -> 122 | C10: =AVERAGE(Dataset_final!H2:H123) -> 2.2143443 | D10: =_xlfn.STDEV.S(Dataset_final!B8:B129) -> 32158.836 | E10: =MIN(Dataset_final!H2:H123) -> 0.05 | F10: =MAX(Dataset_final!H2:H123) -> 5.33
A11: fed_funds_change | B11: =COUNT(Dataset_final!I2:I123) -> 121 | C11: =AVERAGE(Dataset_final!I2:I123) -> 0.027272727 | D11: =_xlfn.STDEV.S(Dataset_final!B9:B130) -> 32158.25 | E11: =MIN(Dataset_final!I2:I123) -> -0.93 | F11: =MAX(Dataset_final!I2:I123) -> 0.7
A12: cpi_index | B12: =COUNT(Dataset_final!J2:J123) -> 122 | C12: =AVERAGE(Dataset_final!J2:J123) -> 276.33693 | D12: =_xlfn.STDEV.S(Dataset_final!B10:B131) -> 32154.704 | E12: =MIN(Dataset_final!J2:J123) -> 237.336 | F12: =MAX(Dataset_final!J2:J123) -> 327.46
A13: inflation_yoy | B13: =COUNT(Dataset_final!K2:K123) -> 110 | C13: =AVERAGE(Dataset_final!K2:K123) -> 0.033298054 | D13: =_xlfn.STDEV.S(Dataset_final!B11:B132) -> 32148.803 | E13: =MIN(Dataset_final!K2:K123) -> 0.001982013 | F13: =MAX(Dataset_final!K2:K123) -> 0.089793611
A14: m2_money_stock | B14: =COUNT(Dataset_final!L2:L123) -> 122 | C14: =AVERAGE(Dataset_final!L2:L123) -> 18008.043 | D14: =_xlfn.STDEV.S(Dataset_final!B12:B133) -> 32140.95 | E14: =MIN(Dataset_final!L2:L123) -> 12518.5 | F14: =MAX(Dataset_final!L2:L123) -> 22627
A15: m2_growth_yoy | B15: =COUNT(Dataset_final!M2:M123) -> 110 | C15: =AVERAGE(Dataset_final!M2:M123) -> 0.063086805 | D15: =_xlfn.STDEV.S(Dataset_final!B13:B134) -> 32130.598 | E15: =MIN(Dataset_final!M2:M123) -> -0.046307908 | F15: =MAX(Dataset_final!M2:M123) -> 0.26775272
A16: btc_volatility_3m | B16: =COUNT(Dataset_final!O2:O123) -> 120 | C16: =AVERAGE(Dataset_final!O2:O123) -> 0.16598088 | D16: =_xlfn.STDEV.S(Dataset_final!B14:B135) -> 32119.273 | E16: =MIN(Dataset_final!O2:O123) -> 0.027528071 | F16: =MAX(Dataset_final!O2:O123) -> 0.41955668
A21: Matriz de correlaciones (desde 2017-01, para alinear variables interanuales)
B22: BTC ret. | C22: S&P ret. | D22: Gold ret. | E22: Δ FEDFUNDS | F22: Inflación YoY | G22: M2 YoY
A23: BTC ret. | B23: =CORREL(Dataset_final!C14:C123,Dataset_final!C14:C123) -> 1 | C23: =CORREL(Dataset_final!C14:C123,Dataset_final!E14:E123) -> 0.35270216 | D23: =CORREL(Dataset_final!C14:C123,Dataset_final!G14:G123) -> 0.066741371 | E23: =CORREL(Dataset_final!C14:C123,Dataset_final!I14:I123) -> -0.087852567 | F23: =CORREL(Dataset_final!C14:C123,Dataset_final!K14:K123) -> -0.2505863 | G23: =CORREL(Dataset_final!C14:C123,Dataset_final!M14:M123) -> 0.13877434
A24: S&P ret. | B24: =CORREL(Dataset_final!E14:E123,Dataset_final!C14:C123) -> 0.35270216 | C24: =CORREL(Dataset_final!E14:E123,Dataset_final!E14:E123) -> 1 | D24: =CORREL(Dataset_final!E14:E123,Dataset_final!G14:G123) -> 0.11058636 | E24: =CORREL(Dataset_final!E14:E123,Dataset_final!I14:I123) -> 0.0083400534 | F24: =CORREL(Dataset_final!E14:E123,Dataset_final!K14:K123) -> -0.17572515 | G24: =CORREL(Dataset_final!E14:E123,Dataset_final!M14:M123) -> 0.097324369
A25: Gold ret. | B25: =CORREL(Dataset_final!G14:G123,Dataset_final!C14:C123) -> 0.066741371 | C25: =CORREL(Dataset_final!G14:G123,Dataset_final!E14:E123) -> 0.11058636 | D25: =CORREL(Dataset_final!G14:G123,Dataset_final!G14:G123) -> 1 | E25: =CORREL(Dataset_final!G14:G123,Dataset_final!I14:I123) -> -0.19415454 | F25: =CORREL(Dataset_final!G14:G123,Dataset_final!K14:K123) -> -0.14803707 | G25: =CORREL(Dataset_final!G14:G123,Dataset_final!M14:M123) -> -0.099633099
A26: Δ FEDFUNDS | B26: =CORREL(Dataset_final!I14:I123,Dataset_final!C14:C123) -> -0.087852567 | C26: =CORREL(Dataset_final!I14:I123,Dataset_final!E14:E123) -> 0.0083400534 | D26: =CORREL(Dataset_final!I14:I123,Dataset_final!G14:G123) -> -0.19415454 | E26: =CORREL(Dataset_final!I14:I123,Dataset_final!I14:I123) -> 1 | F26: =CORREL(Dataset_final!I14:I123,Dataset_final!K14:K123) -> 0.55163757 | G26: =CORREL(Dataset_final!I14:I123,Dataset_final!M14:M123) -> -0.20169367
A27: Inflación YoY | B27: =CORREL(Dataset_final!K14:K123,Dataset_final!C14:C123) -> -0.2505863 | C27: =CORREL(Dataset_final!K14:K123,Dataset_final!E14:E123) -> -0.17572515 | D27: =CORREL(Dataset_final!K14:K123,Dataset_final!G14:G123) -> -0.14803707 | E27: =CORREL(Dataset_final!K14:K123,Dataset_final!I14:I123) -> 0.55163757 | F27: =CORREL(Dataset_final!K14:K123,Dataset_final!K14:K123) -> 1 | G27: =CORREL(Dataset_final!K14:K123,Dataset_final!M14:M123) -> -0.19546276
A28: M2 YoY | B28: =CORREL(Dataset_final!M14:M123,Dataset_final!C14:C123) -> 0.13877434 | C28: =CORREL(Dataset_final!M14:M123,Dataset_final!E14:E123) -> 0.097324369 | D28: =CORREL(Dataset_final!M14:M123,Dataset_final!G14:G123) -> -0.099633099 | E28: =CORREL(Dataset_final!M14:M123,Dataset_final!I14:I123) -> -0.20169367 | F28: =CORREL(Dataset_final!M14:M123,Dataset_final!K14:K123) -> -0.19546276 | G28: =CORREL(Dataset_final!M14:M123,Dataset_final!M14:M123) -> 1
